pylossless/__init__.py
pylossless/_logging.py
pylossless/bids.py
pylossless/conftest.py
pylossless/flagging.py
pylossless/pipeline.py
pylossless/assets/ll_default_config_adults.yaml
pylossless/assets/ll_default_config_infants.yaml
pylossless/assets/test_data/README
pylossless/assets/test_data/dataset_description.json
pylossless/assets/test_data/participants.json
pylossless/assets/test_data/participants.tsv
pylossless/assets/test_data/sub-s01/sub-s01_scans.tsv
pylossless/assets/test_data/sub-s01/eeg/sub-s01_space-CapTrak_coordsystem.json
pylossless/assets/test_data/sub-s01/eeg/sub-s01_space-CapTrak_electrodes.tsv
pylossless/assets/test_data/sub-s01/eeg/sub-s01_task-faceO_channels.tsv
pylossless/assets/test_data/sub-s01/eeg/sub-s01_task-faceO_eeg.edf
pylossless/assets/test_data/sub-s01/eeg/sub-s01_task-faceO_eeg.json
pylossless/assets/test_data/sub-s01/eeg/sub-s01_task-faceO_events.tsv
pylossless/assets/test_data/sub-s01/eeg/sub-s01_task-faceO_ica1_ica.fif
pylossless/assets/test_data/sub-s01/eeg/sub-s01_task-faceO_ica2_ica.fif
pylossless/assets/test_data/sub-s01/eeg/sub-s01_task-faceO_iclabels.tsv
pylossless/assets/test_data/sub-s01/eeg/sub-s01_task-faceO_ll_FlaggedChs.tsv
pylossless/assets/test_data/sub-s01/eeg/sub-s01_task-faceO_ll_config.yaml
pylossless/assets/test_data/sub-s02/sub-s02_scans.tsv
pylossless/assets/test_data/sub-s02/eeg/sub-s02_space-CapTrak_coordsystem.json
pylossless/assets/test_data/sub-s02/eeg/sub-s02_space-CapTrak_electrodes.tsv
pylossless/assets/test_data/sub-s02/eeg/sub-s02_task-faceO_channels.tsv
pylossless/assets/test_data/sub-s02/eeg/sub-s02_task-faceO_eeg.edf
pylossless/assets/test_data/sub-s02/eeg/sub-s02_task-faceO_eeg.json
pylossless/assets/test_data/sub-s02/eeg/sub-s02_task-faceO_events.tsv
pylossless/assets/test_data/sub-s02/eeg/sub-s02_task-faceO_ica1_ica.fif
pylossless/assets/test_data/sub-s02/eeg/sub-s02_task-faceO_ica2_ica.fif
pylossless/assets/test_data/sub-s02/eeg/sub-s02_task-faceO_iclabels.tsv
pylossless-0.2.0.dist-info/LICENSE
pylossless-0.2.0.dist-info/METADATA
pylossless-0.2.0.dist-info/WHEEL
pylossless-0.2.0.dist-info/entry_points.txt
pylossless-0.2.0.dist-info/top_level.txt
pylossless-0.2.0.dist-info/RECORD
