Metadata-Version: 2.1
Name: pylossless
Version: 0.2.0
Summary: Lossless EEG Processing Pipeline Built on MNE and Dash
Home-page: https://github.com/lina-usc/pylossless
Author: Scott Huberty
Author-email: seh33@uw.edu
License-File: LICENSE
Requires-Dist: numpy >=1.21.2
Requires-Dist: mne >=1.5
Requires-Dist: mne-bids >=0.14
Requires-Dist: pandas
Requires-Dist: xarray
Requires-Dist: scipy >=1.7.1
Requires-Dist: mne-icalabel >=0.5.0
Requires-Dist: pyyaml
Requires-Dist: scikit-learn
Provides-Extra: dash
Requires-Dist: gunicorn >=19.8.1 ; extra == 'dash'
Requires-Dist: dash <2.9.0,>=1.0.0 ; extra == 'dash'
Requires-Dist: plotly >=5.4.0 ; extra == 'dash'
Requires-Dist: dash-extensions >=0.1.7 ; extra == 'dash'
Requires-Dist: colorlover >=0.2.1 ; extra == 'dash'
Requires-Dist: dash-bootstrap-components ; extra == 'dash'
Provides-Extra: doc
Requires-Dist: sphinx >=6 ; extra == 'doc'
Requires-Dist: shibuya ; extra == 'doc'
Requires-Dist: sphinx-design ; extra == 'doc'
Requires-Dist: sphinx-gallery ; extra == 'doc'
Requires-Dist: sphinxemoji ; extra == 'doc'
Requires-Dist: numpydoc ; extra == 'doc'
Provides-Extra: test
Requires-Dist: codespell ; extra == 'test'
Requires-Dist: dash[testing] ; extra == 'test'
Requires-Dist: numpydoc ; extra == 'test'
Requires-Dist: pre-commit ; extra == 'test'
Requires-Dist: pytest ; extra == 'test'
Requires-Dist: pytest-cov ; extra == 'test'
Requires-Dist: pydocstyle ; extra == 'test'
Requires-Dist: ruff ; extra == 'test'
Requires-Dist: selenium ; extra == 'test'
Requires-Dist: torch ; extra == 'test'
Requires-Dist: edfio ; extra == 'test'
Requires-Dist: openneuro-py ; extra == 'test'
Requires-Dist: tomli ; (python_version < "3.11") and extra == 'test'
